LICENSE
MANIFEST.in
README.rst
setup.cfg
setup.py
versioneer.py
plottwist/__init__.py
plottwist/bootstrap/__init__.py
plottwist/bootstrap/__logging__.ini
plottwist/bootstrap/__version__.py
plottwist/bootstrap/_version.py
plottwist/bootstrap/houdini/__init__.py
plottwist/bootstrap/houdini/houdini_bootstrap.bat
plottwist/bootstrap/maya/__init__.py
plottwist/bootstrap/maya/userSetup.py
plottwist_bootstrap.egg-info/PKG-INFO
plottwist_bootstrap.egg-info/SOURCES.txt
plottwist_bootstrap.egg-info/dependency_links.txt
plottwist_bootstrap.egg-info/not-zip-safe
plottwist_bootstrap.egg-info/requires.txt
plottwist_bootstrap.egg-info/top_level.txt
tests/__init__.py
tests/test_general.py