Metadata-Version: 2.1
Name: plottwist-bootstrap
Version: 0.0.6
Summary: Repository that contains source code for Plot Twist Bootstrap
Home-page: UNKNOWN
Author: Tomas Poveda
Author-email: tpovedatd@gmail.com
License: MIT
Platform: UNKNOWN
Provides-Extra: dev
Provides-Extra: test
